rdf_to_sqlite/__init__.py
rdf_to_sqlite/cli.py
rdf_to_sqlite/mappings.py
tests/__init__.py
tests/test_cli.py
tests/test_mappings.py
rdf_to_sqlite-0.2.dist-info/LICENSE
rdf_to_sqlite-0.2.dist-info/METADATA
rdf_to_sqlite-0.2.dist-info/WHEEL
rdf_to_sqlite-0.2.dist-info/entry_points.txt
rdf_to_sqlite-0.2.dist-info/top_level.txt
rdf_to_sqlite-0.2.dist-info/RECORD
