Metadata-Version: 2.1
Name: rdf-to-sqlite
Version: 0.2
Summary: Utility for converting an RDF file to SQLite
Home-page: https://github.com/bradleypallen/rdf-to-sqlite
Author: Bradley P. Allen
License: MIT License
Platform: UNKNOWN
Classifier: Development Status :: 3 - Alpha
Classifier: Intended Audience :: Developers
Classifier: Intended Audience :: Science/Research
Classifier: Intended Audience :: End Users/Desktop
Classifier: License :: OSI Approved :: MIT License
Classifier: Operating System :: OS Independent
Classifier: Programming Language :: Python :: 3.8
Classifier: Programming Language :: Python :: 3.9
Requires-Dist: click (>=8.0.1)
Requires-Dist: rdflib (>=6.0.0)
Requires-Dist: sqlite-utils (>=3.12)
Provides-Extra: test
Requires-Dist: pytest ; extra == 'test'
